Metadata-Version: 1.0
Name: django-debug-panel
Version: 0.8.2
Summary: django-debug-toolbar in WebKit DevTools. Works fine with background Ajax requests and non-HTML responses
Home-page: https://github.com/recamshak/django-debug-panel
Author: Joël Billaud
Author-email: jbillaud@gmail.com
License: BSD
Platform: UNKNOWN
